{
  "annotations": {
    "list": [
      {
        "builtIn": 1,
        "datasource": {
          "type": "grafana",
          "uid": "-- Grafana --"
        },
        "enable": true,
        "hide": true,
        "iconColor": "rgba(0, 211, 255, 1)",
        "name": "Annotations & Alerts",
        "type": "dashboard"
      }
    ]
  },
  "editable": true,
  "fiscalYearStartMonth": 0,
  "graphTooltip": 1,
  "links": [],
  "liveNow": true,
  "panels": [
    {
      "datasource": {
        "type": "loki",
        "uid": "Loki"
      },
      "fieldConfig": {
        "defaults": {
          "color": {
            "mode": "palette-classic"
          },
          "custom": {
            "axisCenteredZero": false,
            "axisColorMode": "text",
            "axisLabel": "",
            "axisPlacement": "auto",
            "barAlignment": 0,
            "drawStyle": "line",
            "fillOpacity": 20,
            "gradientMode": "none",
            "hideFrom": {
              "tooltip": false,
              "viz": false,
              "legend": false
            },
            "lineInterpolation": "smooth",
            "lineWidth": 2,
            "pointSize": 5,
            "scaleDistribution": {
              "type": "linear"
            },
            "showPoints": "never",
            "spanNulls": false,
            "stacking": {
              "group": "A",
              "mode": "none"
            },
            "thresholdsStyle": {
              "mode": "off"
            }
          },
          "mappings": [],
          "thresholds": {
            "mode": "absolute",
            "steps": [
              {
                "color": "green",
                "value": null
              }
            ]
          },
          "unit": "reqps"
        },
        "overrides": []
      },
      "gridPos": {
        "h": 8,
        "w": 12,
        "x": 0,
        "y": 0
      },
      "id": 1,
      "options": {
        "legend": {
          "calcs": ["mean", "lastNotNull"],
          "displayMode": "table",
          "placement": "bottom",
          "showLegend": true
        },
        "tooltip": {
          "mode": "multi",
          "sort": "desc"
        }
      },
      "targets": [
        {
          "datasource": {
            "type": "loki",
            "uid": "Loki"
          },
          "editorMode": "code",
          "expr": "sum by (service) (rate({service=~\".+\"} | json [1m]))",
          "queryType": "range",
          "refId": "A"
        }
      ],
      "title": "Request Rate by Service",
      "type": "timeseries"
    },
    {
      "datasource": {
        "type": "loki",
        "uid": "Loki"
      },
      "fieldConfig": {
        "defaults": {
          "color": {
            "mode": "palette-classic"
          },
          "custom": {
            "axisCenteredZero": false,
            "axisColorMode": "text",
            "axisLabel": "",
            "axisPlacement": "auto",
            "barAlignment": 0,
            "drawStyle": "line",
            "fillOpacity": 20,
            "gradientMode": "none",
            "hideFrom": {
              "tooltip": false,
              "viz": false,
              "legend": false
            },
            "lineInterpolation": "smooth",
            "lineWidth": 2,
            "pointSize": 5,
            "scaleDistribution": {
              "type": "linear"
            },
            "showPoints": "never",
            "spanNulls": false,
            "stacking": {
              "group": "A",
              "mode": "none"
            },
            "thresholdsStyle": {
              "mode": "off"
            }
          },
          "mappings": [],
          "thresholds": {
            "mode": "absolute",
            "steps": [
              {
                "color": "green",
                "value": null
              },
              {
                "color": "red",
                "value": 0.01
              }
            ]
          },
          "unit": "percentunit"
        },
        "overrides": []
      },
      "gridPos": {
        "h": 8,
        "w": 12,
        "x": 12,
        "y": 0
      },
      "id": 2,
      "options": {
        "legend": {
          "calcs": ["mean", "lastNotNull"],
          "displayMode": "table",
          "placement": "bottom",
          "showLegend": true
        },
        "tooltip": {
          "mode": "multi",
          "sort": "desc"
        }
      },
      "targets": [
        {
          "datasource": {
            "type": "loki",
            "uid": "Loki"
          },
          "editorMode": "code",
          "expr": "sum by (service) (rate({service=~\".+\"} | json | level=\"error\" [1m])) / sum by (service) (rate({service=~\".+\"} | json [1m]))",
          "queryType": "range",
          "refId": "A"
        }
      ],
      "title": "Error Rate by Service",
      "type": "timeseries"
    },
    {
      "datasource": {
        "type": "loki",
        "uid": "Loki"
      },
      "fieldConfig": {
        "defaults": {
          "color": {
            "mode": "palette-classic"
          },
          "custom": {
            "axisCenteredZero": false,
            "axisColorMode": "text",
            "axisLabel": "",
            "axisPlacement": "auto",
            "barAlignment": 0,
            "drawStyle": "line",
            "fillOpacity": 10,
            "gradientMode": "none",
            "hideFrom": {
              "tooltip": false,
              "viz": false,
              "legend": false
            },
            "lineInterpolation": "smooth",
            "lineWidth": 2,
            "pointSize": 5,
            "scaleDistribution": {
              "type": "linear"
            },
            "showPoints": "never",
            "spanNulls": false,
            "stacking": {
              "group": "A",
              "mode": "none"
            },
            "thresholdsStyle": {
              "mode": "off"
            }
          },
          "mappings": [],
          "thresholds": {
            "mode": "absolute",
            "steps": [
              {
                "color": "green",
                "value": null
              }
            ]
          },
          "unit": "ms"
        },
        "overrides": [
          {
            "matcher": {
              "id": "byName",
              "options": "p50"
            },
            "properties": [
              {
                "id": "color",
                "value": {
                  "fixedColor": "green",
                  "mode": "fixed"
                }
              }
            ]
          },
          {
            "matcher": {
              "id": "byName",
              "options": "p95"
            },
            "properties": [
              {
                "id": "color",
                "value": {
                  "fixedColor": "yellow",
                  "mode": "fixed"
                }
              }
            ]
          },
          {
            "matcher": {
              "id": "byName",
              "options": "p99"
            },
            "properties": [
              {
                "id": "color",
                "value": {
                  "fixedColor": "red",
                  "mode": "fixed"
                }
              }
            ]
          }
        ]
      },
      "gridPos": {
        "h": 8,
        "w": 12,
        "x": 0,
        "y": 8
      },
      "id": 3,
      "options": {
        "legend": {
          "calcs": ["mean", "max"],
          "displayMode": "table",
          "placement": "bottom",
          "showLegend": true
        },
        "tooltip": {
          "mode": "multi",
          "sort": "desc"
        }
      },
      "targets": [
        {
          "datasource": {
            "type": "loki",
            "uid": "Loki"
          },
          "editorMode": "code",
          "expr": "quantile_over_time(0.50, {service=~\".+\"} | json | unwrap duration_ms [1m]) by (service)",
          "legendFormat": "{{service}} - p50",
          "queryType": "range",
          "refId": "A"
        },
        {
          "datasource": {
            "type": "loki",
            "uid": "Loki"
          },
          "editorMode": "code",
          "expr": "quantile_over_time(0.95, {service=~\".+\"} | json | unwrap duration_ms [1m]) by (service)",
          "legendFormat": "{{service}} - p95",
          "queryType": "range",
          "refId": "B"
        },
        {
          "datasource": {
            "type": "loki",
            "uid": "Loki"
          },
          "editorMode": "code",
          "expr": "quantile_over_time(0.99, {service=~\".+\"} | json | unwrap duration_ms [1m]) by (service)",
          "legendFormat": "{{service}} - p99",
          "queryType": "range",
          "refId": "C"
        }
      ],
      "title": "Response Time Percentiles",
      "type": "timeseries"
    },
    {
      "datasource": {
        "type": "loki",
        "uid": "Loki"
      },
      "fieldConfig": {
        "defaults": {
          "color": {
            "mode": "palette-classic"
          },
          "custom": {
            "hideFrom": {
              "tooltip": false,
              "viz": false,
              "legend": false
            }
          },
          "mappings": []
        },
        "overrides": []
      },
      "gridPos": {
        "h": 8,
        "w": 12,
        "x": 12,
        "y": 8
      },
      "id": 4,
      "options": {
        "displayLabels": ["percent"],
        "legend": {
          "displayMode": "table",
          "placement": "right",
          "showLegend": true,
          "values": ["value", "percent"]
        },
        "pieType": "pie",
        "tooltip": {
          "mode": "single",
          "sort": "none"
        }
      },
      "targets": [
        {
          "datasource": {
            "type": "loki",
            "uid": "Loki"
          },
          "editorMode": "code",
          "expr": "sum by (action) (count_over_time({service=~\".+\"} | json | action != \"\" [$__range]))",
          "queryType": "range",
          "refId": "A"
        }
      ],
      "title": "Top Actions by Volume",
      "type": "piechart"
    },
    {
      "datasource": {
        "type": "loki",
        "uid": "Loki"
      },
      "fieldConfig": {
        "defaults": {
          "color": {
            "mode": "thresholds"
          },
          "custom": {
            "align": "auto",
            "cellOptions": {
              "type": "auto"
            },
            "inspect": false
          },
          "mappings": [],
          "thresholds": {
            "mode": "absolute",
            "steps": [
              {
                "color": "green",
                "value": null
              }
            ]
          }
        },
        "overrides": [
          {
            "matcher": {
              "id": "byName",
              "options": "Time"
            },
            "properties": [
              {
                "id": "custom.width",
                "value": 180
              }
            ]
          },
          {
            "matcher": {
              "id": "byName",
              "options": "service"
            },
            "properties": [
              {
                "id": "custom.width",
                "value": 150
              }
            ]
          },
          {
            "matcher": {
              "id": "byName",
              "options": "level"
            },
            "properties": [
              {
                "id": "custom.width",
                "value": 80
              },
              {
                "id": "color",
                "value": {
                  "mode": "thresholds"
                }
              },
              {
                "id": "thresholds",
                "value": {
                  "mode": "absolute",
                  "steps": [
                    {
                      "color": "yellow",
                      "value": null
                    },
                    {
                      "color": "red",
                      "value": 1
                    }
                  ]
                }
              }
            ]
          }
        ]
      },
      "gridPos": {
        "h": 8,
        "w": 24,
        "x": 0,
        "y": 16
      },
      "id": 5,
      "options": {
        "cellHeight": "sm",
        "footer": {
          "countRows": false,
          "fields": "",
          "reducer": ["sum"],
          "show": false
        },
        "showHeader": true
      },
      "targets": [
        {
          "datasource": {
            "type": "loki",
            "uid": "Loki"
          },
          "editorMode": "code",
          "expr": "{service=~\".+\"} | json | level=\"error\"",
          "queryType": "range",
          "refId": "A"
        }
      ],
      "title": "Recent Errors",
      "transformations": [
        {
          "id": "extractFields",
          "options": {
            "format": "json",
            "jsonPaths": [
              {
                "path": "service"
              },
              {
                "path": "level"
              },
              {
                "path": "action"
              },
              {
                "path": "event"
              },
              {
                "path": "error"
              },
              {
                "path": "error_message"
              }
            ],
            "source": "Line"
          }
        },
        {
          "id": "organize",
          "options": {
            "excludeByName": {
              "Line": true,
              "id": true,
              "labels": true,
              "tsNs": true
            },
            "indexByName": {
              "Time": 0,
              "service": 1,
              "level": 2,
              "action": 3,
              "event": 4,
              "error": 5,
              "error_message": 6
            },
            "renameByName": {}
          }
        }
      ],
      "type": "table"
    },
    {
      "datasource": {
        "type": "loki",
        "uid": "Loki"
      },
      "fieldConfig": {
        "defaults": {
          "color": {
            "mode": "palette-classic"
          },
          "custom": {
            "axisCenteredZero": false,
            "axisColorMode": "text",
            "axisLabel": "",
            "axisPlacement": "auto",
            "barAlignment": 0,
            "drawStyle": "bars",
            "fillOpacity": 80,
            "gradientMode": "none",
            "hideFrom": {
              "tooltip": false,
              "viz": false,
              "legend": false
            },
            "lineInterpolation": "linear",
            "lineWidth": 1,
            "pointSize": 5,
            "scaleDistribution": {
              "type": "linear"
            },
            "showPoints": "never",
            "spanNulls": false,
            "stacking": {
              "group": "A",
              "mode": "normal"
            },
            "thresholdsStyle": {
              "mode": "off"
            }
          },
          "mappings": [],
          "thresholds": {
            "mode": "absolute",
            "steps": [
              {
                "color": "green",
                "value": null
              }
            ]
          },
          "unit": "short"
        },
        "overrides": [
          {
            "matcher": {
              "id": "byRegexp",
              "options": "2.."
            },
            "properties": [
              {
                "id": "color",
                "value": {
                  "fixedColor": "green",
                  "mode": "fixed"
                }
              }
            ]
          },
          {
            "matcher": {
              "id": "byRegexp",
              "options": "3.."
            },
            "properties": [
              {
                "id": "color",
                "value": {
                  "fixedColor": "blue",
                  "mode": "fixed"
                }
              }
            ]
          },
          {
            "matcher": {
              "id": "byRegexp",
              "options": "4.."
            },
            "properties": [
              {
                "id": "color",
                "value": {
                  "fixedColor": "yellow",
                  "mode": "fixed"
                }
              }
            ]
          },
          {
            "matcher": {
              "id": "byRegexp",
              "options": "5.."
            },
            "properties": [
              {
                "id": "color",
                "value": {
                  "fixedColor": "red",
                  "mode": "fixed"
                }
              }
            ]
          }
        ]
      },
      "gridPos": {
        "h": 8,
        "w": 12,
        "x": 0,
        "y": 24
      },
      "id": 6,
      "options": {
        "legend": {
          "calcs": ["sum"],
          "displayMode": "table",
          "placement": "bottom",
          "showLegend": true
        },
        "tooltip": {
          "mode": "multi",
          "sort": "desc"
        }
      },
      "targets": [
        {
          "datasource": {
            "type": "loki",
            "uid": "Loki"
          },
          "editorMode": "code",
          "expr": "sum by (status_code) (count_over_time({service=~\".+\"} | json | status_code != \"\" [1m]))",
          "queryType": "range",
          "refId": "A"
        }
      ],
      "title": "HTTP Status Code Distribution",
      "type": "timeseries"
    },
    {
      "datasource": {
        "type": "loki",
        "uid": "Loki"
      },
      "fieldConfig": {
        "defaults": {
          "color": {
            "mode": "thresholds"
          },
          "custom": {
            "align": "auto",
            "cellOptions": {
              "type": "auto"
            },
            "inspect": false
          },
          "mappings": [],
          "thresholds": {
            "mode": "absolute",
            "steps": [
              {
                "color": "green",
                "value": null
              },
              {
                "color": "yellow",
                "value": 500
              },
              {
                "color": "red",
                "value": 1000
              }
            ]
          },
          "unit": "ms"
        },
        "overrides": [
          {
            "matcher": {
              "id": "byName",
              "options": "Time"
            },
            "properties": [
              {
                "id": "custom.width",
                "value": 180
              }
            ]
          },
          {
            "matcher": {
              "id": "byName",
              "options": "duration_ms"
            },
            "properties": [
              {
                "id": "custom.width",
                "value": 100
              },
              {
                "id": "color",
                "value": {
                  "mode": "thresholds"
                }
              }
            ]
          }
        ]
      },
      "gridPos": {
        "h": 8,
        "w": 12,
        "x": 12,
        "y": 24
      },
      "id": 7,
      "options": {
        "cellHeight": "sm",
        "footer": {
          "countRows": false,
          "fields": "",
          "reducer": ["sum"],
          "show": false
        },
        "showHeader": true
      },
      "targets": [
        {
          "datasource": {
            "type": "loki",
            "uid": "Loki"
          },
          "editorMode": "code",
          "expr": "{service=~\".+\"} | json | duration_ms > 500",
          "queryType": "range",
          "refId": "A"
        }
      ],
      "title": "Slow Requests (>500ms)",
      "transformations": [
        {
          "id": "extractFields",
          "options": {
            "format": "json",
            "jsonPaths": [
              {
                "path": "service"
              },
              {
                "path": "action"
              },
              {
                "path": "method"
              },
              {
                "path": "path"
              },
              {
                "path": "duration_ms"
              },
              {
                "path": "status_code"
              }
            ],
            "source": "Line"
          }
        },
        {
          "id": "organize",
          "options": {
            "excludeByName": {
              "Line": true,
              "id": true,
              "labels": true,
              "tsNs": true
            },
            "indexByName": {
              "Time": 0,
              "service": 1,
              "action": 2,
              "method": 3,
              "path": 4,
              "duration_ms": 5,
              "status_code": 6
            },
            "renameByName": {}
          }
        }
      ],
      "type": "table"
    },
    {
      "datasource": {
        "type": "loki",
        "uid": "Loki"
      },
      "fieldConfig": {
        "defaults": {
          "color": {
            "mode": "thresholds"
          },
          "mappings": [
            {
              "options": {
                "match": "null",
                "result": {
                  "text": "0"
                }
              },
              "type": "special"
            }
          ],
          "thresholds": {
            "mode": "absolute",
            "steps": [
              {
                "color": "green",
                "value": null
              },
              {
                "color": "yellow",
                "value": 1
              },
              {
                "color": "red",
                "value": 10
              }
            ]
          },
          "unit": "short"
        },
        "overrides": []
      },
      "gridPos": {
        "h": 4,
        "w": 6,
        "x": 0,
        "y": 32
      },
      "id": 8,
      "options": {
        "colorMode": "background",
        "graphMode": "area",
        "justifyMode": "auto",
        "orientation": "auto",
        "reduceOptions": {
          "values": false,
          "calcs": ["lastNotNull"],
          "fields": ""
        },
        "textMode": "auto"
      },
      "targets": [
        {
          "datasource": {
            "type": "loki",
            "uid": "Loki"
          },
          "editorMode": "code",
          "expr": "sum(count_over_time({service=~\".+\"} | json | level=\"error\" [5m]))",
          "queryType": "range",
          "refId": "A"
        }
      ],
      "title": "Errors (Last 5min)",
      "type": "stat"
    },
    {
      "datasource": {
        "type": "loki",
        "uid": "Loki"
      },
      "fieldConfig": {
        "defaults": {
          "color": {
            "mode": "thresholds"
          },
          "mappings": [],
          "thresholds": {
            "mode": "absolute",
            "steps": [
              {
                "color": "green",
                "value": null
              }
            ]
          },
          "unit": "short"
        },
        "overrides": []
      },
      "gridPos": {
        "h": 4,
        "w": 6,
        "x": 6,
        "y": 32
      },
      "id": 9,
      "options": {
        "colorMode": "value",
        "graphMode": "area",
        "justifyMode": "auto",
        "orientation": "auto",
        "reduceOptions": {
          "values": false,
          "calcs": ["lastNotNull"],
          "fields": ""
        },
        "textMode": "auto"
      },
      "targets": [
        {
          "datasource": {
            "type": "loki",
            "uid": "Loki"
          },
          "editorMode": "code",
          "expr": "sum(count_over_time({service=~\".+\"} | json [5m]))",
          "queryType": "range",
          "refId": "A"
        }
      ],
      "title": "Total Requests (Last 5min)",
      "type": "stat"
    },
    {
      "datasource": {
        "type": "loki",
        "uid": "Loki"
      },
      "fieldConfig": {
        "defaults": {
          "color": {
            "mode": "thresholds"
          },
          "mappings": [],
          "thresholds": {
            "mode": "absolute",
            "steps": [
              {
                "color": "red",
                "value": null
              },
              {
                "color": "yellow",
                "value": 100
              },
              {
                "color": "green",
                "value": 500
              }
            ]
          },
          "unit": "ms"
        },
        "overrides": []
      },
      "gridPos": {
        "h": 4,
        "w": 6,
        "x": 12,
        "y": 32
      },
      "id": 10,
      "options": {
        "colorMode": "value",
        "graphMode": "area",
        "justifyMode": "auto",
        "orientation": "auto",
        "reduceOptions": {
          "values": false,
          "calcs": ["mean"],
          "fields": ""
        },
        "textMode": "auto"
      },
      "targets": [
        {
          "datasource": {
            "type": "loki",
            "uid": "Loki"
          },
          "editorMode": "code",
          "expr": "avg(avg_over_time({service=~\".+\"} | json | unwrap duration_ms [5m]))",
          "queryType": "range",
          "refId": "A"
        }
      ],
      "title": "Avg Response Time (Last 5min)",
      "type": "stat"
    },
    {
      "datasource": {
        "type": "loki",
        "uid": "Loki"
      },
      "fieldConfig": {
        "defaults": {
          "color": {
            "mode": "thresholds"
          },
          "mappings": [],
          "max": 1,
          "min": 0,
          "thresholds": {
            "mode": "percentage",
            "steps": [
              {
                "color": "red",
                "value": null
              },
              {
                "color": "yellow",
                "value": 95
              },
              {
                "color": "green",
                "value": 99
              }
            ]
          },
          "unit": "percentunit"
        },
        "overrides": []
      },
      "gridPos": {
        "h": 4,
        "w": 6,
        "x": 18,
        "y": 32
      },
      "id": 11,
      "options": {
        "orientation": "auto",
        "reduceOptions": {
          "values": false,
          "calcs": ["lastNotNull"],
          "fields": ""
        },
        "showThresholdLabels": false,
        "showThresholdMarkers": true
      },
      "targets": [
        {
          "datasource": {
            "type": "loki",
            "uid": "Loki"
          },
          "editorMode": "code",
          "expr": "sum(rate({service=~\".+\"} | json | status_code < 400 [5m])) / sum(rate({service=~\".+\"} | json [5m]))",
          "queryType": "range",
          "refId": "A"
        }
      ],
      "title": "Success Rate",
      "type": "gauge"
    },
    {
      "datasource": {
        "type": "loki",
        "uid": "Loki"
      },
      "gridPos": {
        "h": 10,
        "w": 24,
        "x": 0,
        "y": 36
      },
      "id": 12,
      "options": {
        "dedupStrategy": "none",
        "enableLogDetails": true,
        "prettifyLogMessage": true,
        "showCommonLabels": false,
        "showLabels": false,
        "showTime": true,
        "sortOrder": "Descending",
        "wrapLogMessage": false
      },
      "targets": [
        {
          "datasource": {
            "type": "loki",
            "uid": "Loki"
          },
          "editorMode": "code",
          "expr": "{service=~\".+\"} | json",
          "queryType": "range",
          "refId": "A"
        }
      ],
      "title": "All Logs",
      "type": "logs"
    }
  ],
  "refresh": "5s",
  "schemaVersion": 38,
  "style": "dark",
  "tags": ["logging", "structured-logs", "loki"],
  "templating": {
    "list": []
  },
  "time": {
    "from": "now-15m",
    "to": "now"
  },
  "timepicker": {},
  "timezone": "",
  "title": "TACA Structured Logging",
  "uid": "taca-logging",
  "version": 1,
  "weekStart": ""
}
